pyr/__init__.py
pyr/bak.py
pyr/cal.py
pyr/ci.py
pyr/cmds.py
pyr/cmds_complex.py
pyr/cons.py
pyr/daiban.py
pyr/env.py
pyr/excel.py
pyr/filebackup_.py
pyr/filecopy.py
pyr/filecopy_n.py
pyr/filedelete.py
pyr/fileedit.py
pyr/filego.py
pyr/fileio.py
pyr/filelistfind.py
pyr/fileopen.py
pyr/filerename.py
pyr/filesystem.py
pyr/fileview.py
pyr/ftp.py
pyr/git.py
pyr/gxxx.py
pyr/ids.py
pyr/kco.py
pyr/keyboard.py
pyr/lastop.py
pyr/ms.py
pyr/mysql.py
pyr/openweb.py
pyr/rconsole.py
pyr/run.py
pyr/rvar.py
pyr/sa.py
pyr/src.py
pyr/ssh.py
pyr/stock.py
pyr/subconsole.py
pyr/svn.py
pyr/tar.py
pyr/tasklist.py
pyr/test_base.py
pyr/test_common.py
pyr/test_fileio.py
pyr/test_filerename.py
pyr/test_ids.py
pyr/test_tar.py
pyr/test_ulist.py
pyr/test_ulog.py
pyr/test_ustring.py
pyr/test_ustring_ops.py
pyr/translate.py
pyr/uhdfs.py
pyr/ulist.py
pyr/ulog.py
pyr/ulog_format.py
pyr/ustring.py
pyr/ustring_ops.py
pyr/utime.py
pyr/uudp.py
pyr/uzip.py
pyr/xiaomi.py
pyrconsole-0.0.3.dist-info/LICENSE
pyrconsole-0.0.3.dist-info/METADATA
pyrconsole-0.0.3.dist-info/WHEEL
pyrconsole-0.0.3.dist-info/top_level.txt
pyrconsole-0.0.3.dist-info/RECORD
