Metadata-Version: 2.1
Name: pyrconsole
Version: 0.0.3
Summary: Python RConsole
Home-page: https://github.com/gzhou/pyrconsole
Author: Guifang Zhou
Author-email: guifang03@126.com
License: UNKNOWN
Project-URL: Bug Tracker, https://github.com/gzhou/pyrconsole/issues
Platform: UNKNOWN
Classifier: Programming Language :: Python :: 3
Classifier: License :: OSI Approved :: MIT License
Classifier: Operating System :: OS Independent
Requires-Python: >=3.6
Requires-Dist: requests (>=2.25.1)
